Metadata-Version: 2.1
Name: kogama.py
Version: 0.1.4
Summary: An API wrapper for the online game KoGaMa written in Python
Home-page: https://github.com/ars3ne/kogama.py
Author: Ars3ne
Author-email: ars3ne@protonmail.com
License: MIT
Keywords: kogama,api
Platform: UNKNOWN
Classifier: Development Status :: 3 - Alpha
Classifier: Intended Audience :: Developers
Classifier: Topic :: Software Development :: Build Tools
Classifier: License :: OSI Approved :: MIT License
Classifier: Programming Language :: Python :: 3.5
Classifier: Programming Language :: Python :: 3.6
Requires-Python: >=3.5.3
